pyplanet/__init__.py
pyplanet/__main__.py
pyplanet/apps/__init__.py
pyplanet/apps/apps.py
pyplanet/apps/config.py
pyplanet/apps/contrib/__init__.py
pyplanet/apps/contrib/admin/__init__.py
pyplanet/apps/contrib/admin/app.py
pyplanet/apps/contrib/admin/flow.py
pyplanet/apps/contrib/admin/forcemapmod.py
pyplanet/apps/contrib/admin/map.py
pyplanet/apps/contrib/admin/mapbrowser.py
pyplanet/apps/contrib/admin/player.py
pyplanet/apps/contrib/admin/pyplanet.py
pyplanet/apps/contrib/admin/server.py
pyplanet/apps/contrib/admin/toolbar.py
pyplanet/apps/contrib/admin/templates/setting/edit.Script.Txt
pyplanet/apps/contrib/admin/templates/setting/edit.xml
pyplanet/apps/contrib/admin/templates/toolbar/toolbar.Script.Txt
pyplanet/apps/contrib/admin/templates/toolbar/toolbar.xml
pyplanet/apps/contrib/admin/views/__init__.py
pyplanet/apps/contrib/admin/views/mapbrowser.py
pyplanet/apps/contrib/admin/views/players.py
pyplanet/apps/contrib/admin/views/setting.py
pyplanet/apps/contrib/admin/views/toolbar.py
pyplanet/apps/contrib/ads/__init__.py
pyplanet/apps/contrib/ads/view.py
pyplanet/apps/contrib/ads/templates/discord_logo.xml
pyplanet/apps/contrib/ads/templates/paypal_logo.xml
pyplanet/apps/contrib/best_cps/__init__.py
pyplanet/apps/contrib/best_cps/view.py
pyplanet/apps/contrib/best_cps/templates/widget_top.xml
pyplanet/apps/contrib/clock/__init__.py
pyplanet/apps/contrib/clock/views.py
pyplanet/apps/contrib/clock/templates/clock.Script.Txt
pyplanet/apps/contrib/clock/templates/clock.xml
pyplanet/apps/contrib/currentcps/__init__.py
pyplanet/apps/contrib/currentcps/app.py
pyplanet/apps/contrib/currentcps/view.py
pyplanet/apps/contrib/currentcps/templates/cpwidget.xml
pyplanet/apps/contrib/dedimania/__init__.py
pyplanet/apps/contrib/dedimania/api.py
pyplanet/apps/contrib/dedimania/app.py
pyplanet/apps/contrib/dedimania/exceptions.py
pyplanet/apps/contrib/dedimania/models.py
pyplanet/apps/contrib/dedimania/views.py
pyplanet/apps/contrib/dynamic_points/__init__.py
pyplanet-0.11.10.dist-info/LICENSE
pyplanet-0.11.10.dist-info/METADATA
pyplanet-0.11.10.dist-info/WHEEL
pyplanet-0.11.10.dist-info/entry_points.txt
pyplanet-0.11.10.dist-info/top_level.txt
pyplanet-0.11.10.dist-info/RECORD
