Metadata-Version: 2.1
Name: pyplanet
Version: 0.11.10
Summary: Maniaplanet Server Controller
Home-page: http://pypla.net/
Author: Tom Valk
Author-email: tomvalk@lt-box.info
License: GNU General Public License v3 (GPLv3)
Keywords: maniaplanet,controller,plugins,apps
Platform: UNKNOWN
Classifier: License :: OSI Approved :: GNU General Public License v3 (GPLv3)
Classifier: Development Status :: 4 - Beta
Classifier: Programming Language :: Python :: 3
Classifier: Programming Language :: Python :: 3.6
Classifier: Programming Language :: Python :: 3.7
Classifier: Programming Language :: Python :: 3.8
Classifier: Programming Language :: Python :: 3 :: Only
Classifier: Operating System :: OS Independent
Classifier: Topic :: Internet
Classifier: Topic :: Software Development
Classifier: Topic :: Games/Entertainment
Classifier: Topic :: Software Development :: Libraries :: Application Frameworks
Classifier: Topic :: Software Development :: Libraries :: Python Modules
Classifier: Intended Audience :: System Administrators
Classifier: Intended Audience :: Developers
Requires-Dist: colorlog==4.8.0
Requires-Dist: Jinja2==2.11.3
Requires-Dist: MarkupSafe==2.0.1
Requires-Dist: peewee==2.10.2
Requires-Dist: peewee-async==0.5.12
Requires-Dist: aiopg<1.0.0
Requires-Dist: aiomysql==0.0.20
Requires-Dist: pymysql==0.9.2
Requires-Dist: aiofiles==0.4.0
Requires-Dist: asyncssh==1.18.0
Requires-Dist: aiohttp==3.8.5
Requires-Dist: async-timeout<5.0,>=4.0.0a3
Requires-Dist: requests==2.27.1
Requires-Dist: urllib3==1.26.5
Requires-Dist: cached-property==1.5.2
Requires-Dist: watchdog==0.10.2
Requires-Dist: async-generator==1.10
Requires-Dist: asyncio-extras==1.3.2
Requires-Dist: bcrypt==3.2.0
Requires-Dist: raven==6.10.0
Requires-Dist: xmltodict==0.12.0
Requires-Dist: PyYAML==6.0.2
Requires-Dist: packaging<=23.1
Requires-Dist: cryptography==40.0.2
